oc_opsdevnz/__init__.py
oc_opsdevnz/cli.py
oc_opsdevnz/oc_client.py
oc_opsdevnz/operations.py
oc_opsdevnz/secrets.py
oc_opsdevnz-0.2.3.dist-info/licenses/LICENSE
oc_opsdevnz-0.2.3.dist-info/METADATA
oc_opsdevnz-0.2.3.dist-info/WHEEL
oc_opsdevnz-0.2.3.dist-info/entry_points.txt
oc_opsdevnz-0.2.3.dist-info/top_level.txt
oc_opsdevnz-0.2.3.dist-info/RECORD
