Metadata-Version: 2.4
Name: oc-opsdevnz
Version: 0.2.3
Summary: OpenCollective API helper (OpsDev.nz), prod-default with 1Password token resolution
Author: John Billings
Requires-Python: >=3.10
License-File: LICENSE
Requires-Dist: httpx>=0.27.0
Requires-Dist: op-opsdevnz>=0.1.0
Requires-Dist: PyYAML>=6.0
Provides-Extra: dev
Requires-Dist: build>=1.2.1; extra == "dev"
Requires-Dist: pytest>=7.4; extra == "dev"
Requires-Dist: respx>=0.20.0; extra == "dev"
Requires-Dist: ruff>=0.6.0; extra == "dev"
Dynamic: license-file
